dotGraph/__init__.py
dotGraph/main.py
dotGraph_Rhy-0.0.7.dist-info/LICENSE
dotGraph_Rhy-0.0.7.dist-info/METADATA
dotGraph_Rhy-0.0.7.dist-info/WHEEL
dotGraph_Rhy-0.0.7.dist-info/entry_points.txt
dotGraph_Rhy-0.0.7.dist-info/top_level.txt
dotGraph_Rhy-0.0.7.dist-info/zip-safe
dotGraph_Rhy-0.0.7.dist-info/RECORD
